admin_api_lib/__init__.py
admin_api_lib/api_endpoints/document_deleter.py
admin_api_lib/api_endpoints/document_reference_retriever.py
admin_api_lib/api_endpoints/documents_status_retriever.py
admin_api_lib/api_endpoints/file_uploader.py
admin_api_lib/api_endpoints/source_uploader.py
admin_api_lib/api_endpoints/uploader_base.py
admin_api_lib/apis/__init__.py
admin_api_lib/apis/admin_api.py
admin_api_lib/apis/admin_api_base.py
admin_api_lib/chunker/__init__.py
admin_api_lib/chunker/chunker.py
admin_api_lib/dependency_container.py
admin_api_lib/extractor_api_client/__init__.py
admin_api_lib/extractor_api_client/openapi_client/__init__.py
admin_api_lib/extractor_api_client/openapi_client/api/__init__.py
admin_api_lib/extractor_api_client/openapi_client/api/extractor_api.py
admin_api_lib/extractor_api_client/openapi_client/api_client.py
admin_api_lib/extractor_api_client/openapi_client/api_response.py
admin_api_lib/extractor_api_client/openapi_client/configuration.py
admin_api_lib/extractor_api_client/openapi_client/exceptions.py
admin_api_lib/extractor_api_client/openapi_client/models/__init__.py
admin_api_lib/extractor_api_client/openapi_client/models/content_type.py
admin_api_lib/extractor_api_client/openapi_client/models/extraction_parameters.py
admin_api_lib/extractor_api_client/openapi_client/models/extraction_request.py
admin_api_lib/extractor_api_client/openapi_client/models/information_piece.py
admin_api_lib/extractor_api_client/openapi_client/models/key_value_pair.py
admin_api_lib/extractor_api_client/openapi_client/rest.py
admin_api_lib/extractor_api_client/openapi_client/test/__init__.py
admin_api_lib/extractor_api_client/openapi_client/test/test_content_type.py
admin_api_lib/extractor_api_client/openapi_client/test/test_extraction_parameters.py
admin_api_lib/extractor_api_client/openapi_client/test/test_extraction_request.py
admin_api_lib/extractor_api_client/openapi_client/test/test_extractor_api.py
admin_api_lib-3.4.0.dist-info/METADATA
admin_api_lib-3.4.0.dist-info/WHEEL
admin_api_lib-3.4.0.dist-info/RECORD
