Metadata-Version: 2.4
Name: admin-api-lib
Version: 3.4.0
Summary: The admin backend is responsible for the document management. This includes deletion, upload and returning the source document.
License: Apache-2.0
Author: STACKIT GmbH & Co. KG
Author-email: data-ai@stackit.cloud
Maintainer: Andreas Klos
Maintainer-email: andreas.klos@stackit.cloud
Requires-Python: >=3.13,<4.0
Classifier: License :: OSI Approved :: Apache Software License
Classifier: Programming Language :: Python :: 3
Classifier: Programming Language :: Python :: 3.13
Classifier: Programming Language :: Python :: 3.14
Requires-Dist: boto3 (>=1.38.10,<2.0.0)
Requires-Dist: dependency-injector (>=4.46.0,<5.0.0)
Requires-Dist: fastapi (>=0.118.0,<0.119.0)
Requires-Dist: langchain-experimental (>=0.3.4,<0.4.0)
Requires-Dist: langfuse (==3.6.1)
Requires-Dist: nltk (>=3.9.2,<4.0.0)
Requires-Dist: python-dateutil (>=2.9.0.post0,<3.0.0)
Requires-Dist: python-multipart (>=0.0.20,<0.0.21)
Requires-Dist: pyyaml (>=6.0.2,<7.0.0)
Requires-Dist: rag-core-lib (==3.4.0)
Requires-Dist: redis (>=6.0.0,<7.0.0)
Requires-Dist: starlette (>=0.47.2,<0.49.0)
Requires-Dist: tenacity (==9.1.2)
Requires-Dist: tqdm (>=4.67.1,<5.0.0)
Requires-Dist: uvicorn (>=0.37.0,<0.38.0)
Project-URL: Homepage, https://pypi.org/project/admin-api-lib
Project-URL: Repository, https://github.com/stackitcloud/rag-template
